pygamemaker/__init__.py
pygamemaker/pyplayground.py
pygamemaker-0.0.1.dist-info/LICENCE
pygamemaker-0.0.1.dist-info/METADATA
pygamemaker-0.0.1.dist-info/WHEEL
pygamemaker-0.0.1.dist-info/top_level.txt
pygamemaker-0.0.1.dist-info/RECORD
