Metadata-Version: 2.1
Name: pygamemaker
Version: 0.0.1
Summary: For when you want to make games
Home-page: https://github.com/ianyourgod/pygamemaker
Author: ianyourgod
Author-email: ianyourgod@gmail.com
Classifier: Programming Language :: Python :: 3
Classifier: License :: OSI Approved :: MIT License
Classifier: Operating System :: OS Independent
Requires-Python: >=3.7
License-File: LICENCE
